emitter/__init__.py
emitter/emitter.py
emitter/emitter_test.py
emitter/sample-python2.py
emitter/sample-python3.py
emitter/subtrie.py
emitter/subtrie_test.py
emitter_io-2.3.0.dist-info/LICENSE
emitter_io-2.3.0.dist-info/METADATA
emitter_io-2.3.0.dist-info/WHEEL
emitter_io-2.3.0.dist-info/top_level.txt
emitter_io-2.3.0.dist-info/RECORD
