Metadata-Version: 2.1
Name: emitter-io
Version: 2.3.0
Summary: A Python library to interact with the Emitter API.
Home-page: https://emitter.io
Author: Florimond Husquinet
Author-email: florimond@emitter.io
License: UNKNOWN
Keywords: emitter mqtt realtime cloud service
Platform: UNKNOWN
Classifier: Development Status :: 5 - Production/Stable
Classifier: Intended Audience :: Developers
Classifier: Topic :: Communications
Classifier: Topic :: Internet :: WWW/HTTP
Classifier: License :: OSI Approved :: Eclipse Public License 1.0 (EPL-1.0)
Classifier: Programming Language :: Python :: 2
Classifier: Programming Language :: Python :: 3
Requires-Dist: paho-mqtt
